mirge_build/__init__.py
mirge_build/__main__.py
mirge_build/blibs/__init__.py
mirge_build/blibs/bldparse.py
mirge_build/blibs/miRge_bowtie_build.py
mirge_build/blibs/miRge_pckls_build.py
miRge_build-0.0.1.dist-info/LICENSE
miRge_build-0.0.1.dist-info/METADATA
miRge_build-0.0.1.dist-info/WHEEL
miRge_build-0.0.1.dist-info/entry_points.txt
miRge_build-0.0.1.dist-info/top_level.txt
miRge_build-0.0.1.dist-info/RECORD
