Metadata-Version: 2.1
Name: miRge-build
Version: 0.0.1
Summary: miRge-build: Building libraries of small RNA sequencing Data
Home-page: https://github.com/mhalushka/miRge3_build
Author: Arun Patil and Marc Halushka
Author-email: mhalush1@jhmi.edu
License: MIT
Keywords: miRge-build,small RNA analysis,NGS,bioinformatics tools
Platform: UNKNOWN
Classifier: Development Status :: 1 - Planning
Classifier: Environment :: Console
Classifier: Intended Audience :: Science/Research
Classifier: License :: OSI Approved :: MIT License
Classifier: Natural Language :: English
Classifier: Programming Language :: Python :: 3.8
Classifier: Topic :: Scientific/Engineering :: Bio-Informatics
Requires-Python: >=3.8
Requires-Dist: biopython (==1.77)
Requires-Dist: scikit-learn (==0.23.1)
Requires-Dist: scipy (==1.4.1)
